uhugo/__init__.py
uhugo/checks.py
uhugo/cmd.py
uhugo/download.py
uhugo/install.py
uhugo/utils.py
uhugo/post_install/__init__.py
uhugo/post_install/detect_providers.py
uhugo/post_install/update_providers.py
uhugo/post_install/providers/__init__.py
uhugo/post_install/providers/cloudflare.py
uhugo/post_install/providers/netlify.py
uhugo/post_install/providers/vercel.py
uhugo/terminal_commands/__init__.py
uhugo/terminal_commands/posix.py
uhugo/terminal_commands/windows.py
uhugo-1.4.2.dist-info/METADATA
uhugo-1.4.2.dist-info/WHEEL
uhugo-1.4.2.dist-info/entry_points.txt
uhugo-1.4.2.dist-info/licenses/LICENSE
uhugo-1.4.2.dist-info/RECORD
