Metadata-Version: 2.4
Name: uhugo
Version: 1.4.2
Summary: uHugo is a CLI tool to install and update Hugo binary as well as updating any cloud providers
Project-URL: Homepage, https://github.com/akshaybabloo/uhugo
Project-URL: Documentation, https://akshaybabloo.github.io/uHugo/
Project-URL: Repository, https://github.com/akshaybabloo/uhugo.git
Project-URL: Issues, https://github.com/akshaybabloo/uhugo/issues
Author-email: Akshay Raj Gollahalli <akshay@gollahalli.com>
License: MIT License
License-File: LICENSE
Keywords: hugo,hugo cli helper
Classifier: Development Status :: 5 - Production/Stable
Classifier: Environment :: Console
Classifier: Intended Audience :: Developers
Classifier: License :: OSI Approved :: MIT License
Classifier: Programming Language :: Python :: 3 :: Only
Classifier: Programming Language :: Python :: 3.10
Classifier: Programming Language :: Python :: 3.11
Classifier: Programming Language :: Python :: 3.12
Classifier: Programming Language :: Python :: 3.13
Classifier: Topic :: Utilities
Requires-Python: >=3.10
Requires-Dist: click>=8.1.8
Requires-Dist: packaging>=24.2
Requires-Dist: psutil>=6.1.1
Requires-Dist: pydantic>=2.10.4
Requires-Dist: pyyaml>=6.0.2
Requires-Dist: requests>=2.32.3
Requires-Dist: rich>=13.9.4
Requires-Dist: toml>=0.10.2
